edf_reader/__init__.py
edf_reader-0.1.2.dist-info/METADATA
edf_reader-0.1.2.dist-info/WHEEL
edf_reader-0.1.2.dist-info/top_level.txt
edf_reader-0.1.2.dist-info/RECORD
