Metadata-Version: 2.4
Name: edf-reader
Version: 0.1.2
Summary: Lightweight EDF file reader, which can handle discontinuities.
Home-page: https://gitlab.com/bbeer_group/development/epycom/edf_reader
Author: Vojtech Travnicek
Author-email: Vojtech Travnicek <vojtech.travnicek@fnusa.cz>
License: BSD-3-Clause
Project-URL: Homepage, https://gitlab.com/bbeer_group/development/epycom/edf_reader
Keywords: edf,edf+,edf+d,european data format,eeg,medical,neuroscience
Classifier: Development Status :: 4 - Beta
Classifier: Intended Audience :: Science/Research
Classifier: Intended Audience :: Healthcare Industry
Classifier: License :: OSI Approved :: BSD License
Classifier: Programming Language :: Python :: 3
Classifier: Programming Language :: Python :: 3.12
Classifier: Operating System :: OS Independent
Classifier: Topic :: Scientific/Engineering :: Medical Science Apps.
Classifier: Topic :: Scientific/Engineering :: Bio-Informatics
Requires-Python: >=3.12
Requires-Dist: numpy
Provides-Extra: dev
Requires-Dist: pytest; extra == "dev"
Dynamic: author
Dynamic: home-page
Dynamic: requires-python
